pyfunnel/__init__.py
pyfunnel/cli.py
pyfunnel/core.py
pyfunnel/lib/darwin64/libfunnel.dylib
pyfunnel/lib/linux64/libfunnel.so
pyfunnel/lib/win64/funnel.dll
pyfunnel/lib/win64/funnel.lib
pyfunnel/templates/plot.html
pyfunnel-2.0.1.dist-info/licenses/LICENSE.txt
pyfunnel-2.0.1.dist-info/METADATA
pyfunnel-2.0.1.dist-info/WHEEL
pyfunnel-2.0.1.dist-info/entry_points.txt
pyfunnel-2.0.1.dist-info/top_level.txt
pyfunnel-2.0.1.dist-info/RECORD
