Metadata-Version: 2.4
Name: pyfunnel
Version: 2.0.1
Summary: Comparison tool for two (x, y) data sets given tolerances in x and y directions
Author-email: "A. Gautier" <agautier@lbl.gov>
Project-URL: Homepage, https://github.com/lbl-srg/funnel
Classifier: Development Status :: 5 - Production/Stable
Classifier: Environment :: Console
Classifier: License :: OSI Approved :: BSD License
Classifier: Programming Language :: Python :: 3.8
Classifier: Programming Language :: C
Classifier: Intended Audience :: End Users/Desktop
Classifier: Intended Audience :: Science/Research
Classifier: Topic :: Scientific/Engineering
Classifier: Topic :: Utilities
Requires-Python: >=3.8
License-File: LICENSE.txt
Provides-Extra: dev
Requires-Dist: pandas>=2.0.0; extra == "dev"
Provides-Extra: publish
Requires-Dist: commitizen>=4.8.2; extra == "publish"
Requires-Dist: twine>=6.1.0; extra == "publish"
Requires-Dist: build>=1.0.0; extra == "publish"
Requires-Dist: packaging>=25.0; extra == "publish"
Dynamic: license-file
